mihaela_presentation/__init__.py
mihaela_presentation/mihaela.py
mihaela_presentation-0.1.3.dist-info/METADATA
mihaela_presentation-0.1.3.dist-info/WHEEL
mihaela_presentation-0.1.3.dist-info/top_level.txt
mihaela_presentation-0.1.3.dist-info/RECORD
