Metadata-Version: 2.1
Name: mihaela-presentation
Version: 0.1.3
Summary: My first project in pypi
Home-page: UNKNOWN
Author: Mihaela M.
Author-email: miha_baci@yahoo.com
License: UNKNOWN
Platform: UNKNOWN
